v3_liquidity_pool_simulator/__init__.py
v3_liquidity_pool_simulator/simulator.py
v3_liquidity_pool_simulator-0.2.1.dist-info/METADATA
v3_liquidity_pool_simulator-0.2.1.dist-info/WHEEL
v3_liquidity_pool_simulator-0.2.1.dist-info/top_level.txt
v3_liquidity_pool_simulator-0.2.1.dist-info/RECORD
