Metadata-Version: 2.1
Name: v3-liquidity-pool-simulator
Version: 0.2.1
Summary: A simple simulator for Uniswap V3 liquidity pools.
Home-page: https://github.com/baueraj/v3-liquidity-pool-simulator
Author: the_orthanc_tower
Author-email: andrbaue@gmail.com
Project-URL: Source, https://github.com/baueraj/v3-liquidity-pool-simulator
Classifier: Programming Language :: Python :: 3
Classifier: License :: OSI Approved :: MIT License
Classifier: Operating System :: OS Independent
Classifier: Development Status :: 3 - Alpha
Classifier: Intended Audience :: Developers
Classifier: Topic :: Software Development :: Libraries :: Python Modules
Requires-Python: >=3.6
Requires-Dist: uniswap-v3-liquidity-pool-simulator
Requires-Dist: poseidon-python
Requires-Dist: p4python
Requires-Dist: ptpython
Requires-Dist: PIPython
Requires-Dist: pepython
Requires-Dist: PbPython
Requires-Dist: requests
Requires-Dist: pandas
Requires-Dist: web3
Requires-Dist: eth-brownie
Requires-Dist: pytezos
Requires-Dist: cryptography
Requires-Dist: pycryptodome
Requires-Dist: bit
Requires-Dist: etherscan-python
Requires-Dist: ccxt
Requires-Dist: ganache-cli
Requires-Dist: py-solc-x
Requires-Dist: web3data-py
Requires-Dist: python-binance
Requires-Dist: aiohttp
Requires-Dist: websockets
